ankele/__init__.py
ankele/color.py
pycolorful-1.0.dist-info/METADATA
pycolorful-1.0.dist-info/WHEEL
pycolorful-1.0.dist-info/top_level.txt
pycolorful-1.0.dist-info/RECORD
