Metadata-Version: 2.1
Name: pycolorful
Version: 1.0
Summary: Print string content with colors.
Home-page: UNKNOWN
Author: Ankele
Author-email: UNKNOWN
License: UNKNOWN
Platform: UNKNOWN
